facebook_scraper_vn/__init__.py
facebook_scraper_vn/_jscode.py
facebook_scraper_vn/_utils.py
facebook_scraper_vn/facebook_scraper.py
test/__init__.py
test/main.py
facebook_scraper_vn-0.0.1.dist-info/METADATA
facebook_scraper_vn-0.0.1.dist-info/WHEEL
facebook_scraper_vn-0.0.1.dist-info/top_level.txt
facebook_scraper_vn-0.0.1.dist-info/RECORD
