Metadata-Version: 2.1
Name: facebook_scraper_vn
Version: 0.0.1
Summary: Scraping facebook page tool
Author-email: Le Duc Phuong <phuongtroc2004@gmail.com>
Project-URL: Homepage, https://github.com/leducphuong19122004/Facebook-Scraping
Keywords: facebook,scrape,crawl,page
Classifier: Programming Language :: Python :: 3
Classifier: License :: OSI Approved :: MIT License
Classifier: Operating System :: OS Independent
Requires-Python: >=3.8
Requires-Dist: playwright >=1.43.0
Requires-Dist: urllib3 >=2.2.1
Requires-Dist: requests >=2.31.0
Requires-Dist: pathlib >=1.0.1
